{
  "kind": "collectionType",
  "collectionName": "seos",
  "info": {
    "singularName": "seo",
    "pluralName": "seos",
    "displayName": "SEO",
    "description": ""
  },
  "options": {
    "draftAndPublish": false
  },
  "pluginOptions": {
    "i18n": {
      "localized": true
    }
  },
  "attributes": {
    "title": {
      "pluginOptions": {
        "i18n": {
          "localized": true
        }
      },
      "type": "string",
      "required": true
    },
    "description": {
      "pluginOptions": {
        "i18n": {
          "localized": true
        }
      },
      "type": "text",
      "required": false
    },
    "keywords": {
      "pluginOptions": {
        "i18n": {
          "localized": true
        }
      },
      "type": "string",
      "required": false
    },
    "image": {
      "type": "media",
      "multiple": false,
      "required": false,
      "allowedTypes": [
        "images"
      ],
      "pluginOptions": {
        "i18n": {
          "localized": true
        }
      }
    }
  }
}
